lnkshrt_cli/__init__.py
lnkshrt_cli/__main__.py
lnkshrt_cli/config.py
lnkshrt_cli/main.py
lnkshrt_cli/utils.py
lnkshrt_cli-0.1.0.dist-info/LICENSE
lnkshrt_cli-0.1.0.dist-info/METADATA
lnkshrt_cli-0.1.0.dist-info/WHEEL
lnkshrt_cli-0.1.0.dist-info/entry_points.txt
lnkshrt_cli-0.1.0.dist-info/RECORD
