Metadata-Version: 2.1
Name: lnkshrt-cli
Version: 0.1.0
Summary: lnkshrt-cli is a command-line interface (CLI) tool for interacting with the lnkshrt link shortening API. It provides a convenient way to manage and utilize the features of the lnkshrt API directly from the command line.
License: MIT
Author: vivekashok1221
Author-email: vivekashok1221@gmail.com
Requires-Python: >=3.11,<4.0
Classifier: License :: OSI Approved :: MIT License
Classifier: Programming Language :: Python :: 3
Classifier: Programming Language :: Python :: 3.11
Requires-Dist: httpx (>=0.24.1,<0.25.0)
Requires-Dist: loguru (>=0.7.0,<0.8.0)
Requires-Dist: qrcode (>=7.4.2,<8.0.0)
Requires-Dist: tomlkit (>=0.11.8,<0.12.0)
Requires-Dist: typer[all] (>=0.9.0,<0.10.0)
